jsong.py
jsong-0.9.dist-info/METADATA
jsong-0.9.dist-info/WHEEL
jsong-0.9.dist-info/top_level.txt
jsong-0.9.dist-info/RECORD
