Metadata-Version: 2.1
Name: jsong
Version: 0.9
Summary: Transforms website data from allmusic.com into programmatically usable json and excel files
Author: OakTree
Author-email: thefirstoaktree@gmail.com
Classifier: Programming Language :: Python :: 3
Classifier: License :: OSI Approved :: MIT License
Classifier: Operating System :: OS Independent
